README.md
setup.py
conker/__init__.py
conker.egg-info/PKG-INFO
conker.egg-info/SOURCES.txt
conker.egg-info/dependency_links.txt
conker.egg-info/top_level.txt