Metadata-Version: 1.0
Name: conker
Version: 0.1
Summary: Contracts (preconditions, postconditions)
Home-page: https://github.com/byxor/conker
Author: Brandon Ibbotson
Author-email: UNKNOWN
License: GPLv3
Platform: UNKNOWN
